{
  "screenId": "character-ds3-main",
  "rendering": {
    "nodeCount": 156,
    "maxDepth": 12,
    "estimatedDrawCalls": 2,
    "colorRectCount": 0
  },
  "loading": {
    "atlasCount": 1,
    "atlasLimit": 4,
    "preloadSpriteCount": 1,
    "deferredSpriteCount": 0,
    "estimatedTextureBytes": 262144,
    "fontCount": 1
  },
  "lifecycle": {
    "lazySlotCount": 0,
    "warmupHints": {
      "next-frame": 0,
      "idle": 0,
      "tab-hover": 0,
      "manual": 0
    }
  },
  "runtimeGate": {
    "nodeCount": {
      "value": 156,
      "warning": 35,
      "blocker": 60,
      "status": "fail",
      "acceptedException": {
        "reason": "multi-tab-content-page",
        "rationale": "6-tab character profile: 76 labels + 33 panels reflect real content density. Active subtree ~26 nodes per tab when lazy-loaded; total 156 is the union of all tabs at design-time.",
        "effectiveActiveBudget": 60,
        "estimatedActiveNodes": 50,
        "mitigation": "tab-level ChildPanel lazy-mount via bundle-suggestion"
      }
    },
    "maxDepth": {
      "value": 12,
      "warning": 8,
      "blocker": 12,
      "status": "warn"
    }
  },
  "verdict": {
    "level": "warn",
    "warnings": [
      "node-count-warn-accepted: total=156 with tab-lazy-load mitigation",
      "max-depth-warning: 12 (>8)"
    ],
    "blockers": []
  }
}