{
  "type": "container",
  "name": "BloodlineOverviewModules",
  "widget": { "top": 372, "left": 18, "right": 18 },
  "height": 314,
  "children": [
    {
      "type": "container",
      "name": "BloodlineRow",
      "widget": { "top": 0, "left": 0, "right": 0 },
      "height": 314,
      "children": [
        {
          "type": "panel",
          "name": "BloodlineUnifiedCard",
          "widget": { "top": 0, "left": 0, "right": 0, "bottom": 0 },
          "skinSlot": "gdv3.bloodline.unified.card",
          "children": [
            {
              "type": "image",
              "name": "BloodlineUnifiedBand",
              "widget": { "top": 16, "left": 20, "right": 20 },
              "height": 40,
              "skinSlot": "gdv3.header.band"
            },
            { "type": "label", "name": "BloodlineCardTitle", "widget": { "top": 22, "left": 32, "right": 280 }, "height": 28, "styleSlot": "gdv3.label.sectionBand" },
            {
              "type": "container",
              "name": "BloodlineSummaryCard",
              "widget": { "top": 74, "left": 28, "bottom": 22, "right": 280 },
              "children": [
                {
                  "type": "container",
                  "name": "BloodlineSummaryFields",
                  "widget": { "top": 8, "left": 0, "right": 0 },
                  "height": 144,
                  "layout": { "type": "vertical", "spacing": 4 },
                  "children": [
                    { "type": "label", "name": "BloodlineTitle", "widget": { "left": 0, "right": 0 }, "width": "100%", "height": 18, "styleSlot": "gdv3.label.meta" },
                    { "type": "label", "name": "BloodlineName", "widget": { "left": 0, "right": 0 }, "width": "100%", "height": 30, "styleSlot": "gdv3.label.value" },
                    {
                      "type": "container",
                      "name": "AwakeningProgressGroup",
                      "widget": { "left": 0, "right": 0 },
                      "width": "100%",
                      "height": 40,
                      "layout": { "type": "vertical", "spacing": 4 },
                      "children": [
                        { "type": "label", "name": "AwakeningLabel", "widget": { "left": 0, "right": 0 }, "width": "100%", "height": 18, "styleSlot": "gdv3.label.meta" },
                        {
                          "type": "panel",
                          "name": "AwakeningBarTrack",
                          "width": "66%",
                          "height": 12,
                          "skinSlot": "gdv3.progress.track",
                          "children": [
                            {
                              "type": "image",
                              "name": "AwakeningBarFill",
                              "widget": { "top": 0, "bottom": 0, "left": 0 },
                              "width": "100%",
                              "skinSlot": "gdv3.progress.fill"
                            }
                          ]
                        }
                      ]
                    },
                    { "type": "label", "name": "PersonalityLabel", "widget": { "left": 0, "right": 0 }, "width": "100%", "height": 18, "styleSlot": "gdv3.label.meta" },
                    { "type": "label", "name": "PersonalityValue", "widget": { "left": 0, "right": 0 }, "width": "100%", "height": 18, "styleSlot": "gdv3.label.note" }
                  ]
                },
                { "type": "label", "name": "BloodlineBody", "widget": { "top": 164, "bottom": 0, "left": 0, "right": 0 }, "styleSlot": "gdv3.label.cardBody" }
              ]
            },
            {
              "type": "panel",
              "name": "BloodlineDivider",
              "widget": { "top": 72, "bottom": 22, "right": 248 },
              "width": 2,
              "skinSlot": "gdv3.bloodline.divider"
            },
            {
              "type": "container",
              "name": "BloodlineCrestCard",
              "widget": { "top": 74, "right": 24, "bottom": 22 },
              "width": 212,
              "children": [
                { "type": "label", "name": "CrestTitle", "widget": { "top": 0, "left": 0, "right": 0 }, "height": 28, "styleSlot": "gdv3.label.sectionBand" },
                { "type": "label", "name": "CrestHint", "widget": { "top": 34, "left": 0, "right": 0 }, "height": 28, "styleSlot": "gdv3.label.note" },
                {
                  "type": "container",
                  "name": "BloodlineCrestCarrier",
                  "widget": { "top": 68, "bottom": 0, "left": 0, "right": 0 },
                  "children": [
                    {
                      "type": "image",
                      "name": "BloodlineCrestGlow",
                      "widget": { "hCenter": true, "vCenter": 2 },
                      "width": 172,
                      "height": 172,
                      "skinSlot": "gdv3.bloodline.crest.glow"
                    },
                    {
                      "type": "image",
                      "name": "BloodlineCrestFill",
                      "widget": { "hCenter": true, "vCenter": 2 },
                      "width": 148,
                      "height": 148,
                      "skinSlot": "gdv3.bloodline.crest.fill"
                    },
                    {
                      "type": "image",
                      "name": "BloodlineCrestInnerRing",
                      "widget": { "hCenter": true, "vCenter": 2 },
                      "width": 158,
                      "height": 158,
                      "skinSlot": "gdv3.bloodline.crest.inner"
                    },
                    {
                      "type": "image",
                      "name": "BloodlineCrest",
                      "widget": { "hCenter": true, "vCenter": 2 },
                      "width": 132,
                      "height": 132,
                      "skinSlot": "gdv3.bloodline.crest"
                    },
                    {
                      "type": "label",
                      "name": "CrestGlyphSecondary",
                      "widget": { "top": 28, "left": 34, "right": 34 },
                      "height": 18,
                      "styleSlot": "gdv3.label.crestGlyphSecondary"
                    },
                    {
                      "type": "label",
                      "name": "CrestGlyphPrimary",
                      "widget": { "top": 46, "bottom": 46, "left": 34, "right": 34 },
                      "styleSlot": "gdv3.label.crestGlyphPrimary"
                    },
                    {
                      "type": "image",
                      "name": "BloodlineCrestFrame",
                      "widget": { "hCenter": true, "vCenter": 2 },
                      "width": 170,
                      "height": 170,
                      "skinSlot": "gdv3.bloodline.crest.frame"
                    },
                    {
                      "type": "image",
                      "name": "BloodlineCrestFace",
                      "widget": { "hCenter": true, "vCenter": 2 },
                      "width": 120,
                      "height": 120,
                      "skinSlot": "gdv3.bloodline.crest.face"
                    },
                    {
                      "type": "label",
                      "name": "CrestStateLabel",
                      "widget": { "left": 18, "right": 18, "bottom": 10 },
                      "height": 22,
                      "styleSlot": "gdv3.label.crestState"
                    }
                  ]
                }
              ]
            }
          ]
        }
      ]
    }
  ]
}
